{"options":{"type":"mixed","multi":false,"allowSelfLoops":true},"attributes":{},"nodes":[{"key":"0","attributes":{"label":"emilia_Bones_","size":15,"x":8,"y":-10,"c":0}},{"key":"1","attributes":{"label":"7KroNe","size":6,"x":-72,"y":-4,"c":1}},{"key":"2","attributes":{"label":"MeufsTeubs","size":6,"x":-78,"y":-41,"c":1}},{"key":"3","attributes":{"label":"Jarm0u","size":4,"x":-67,"y":14,"c":2}},{"key":"4","attributes":{"label":"MelleBene","size":3,"x":-42,"y":-56,"c":3}},{"key":"5","attributes":{"label":"PrincessSynahel","size":3,"x":-81,"y":-13,"c":2}},{"key":"6","attributes":{"label":"AccidentaLeftFR","size":4,"x":-23,"y":14,"c":3}},{"key":"7","attributes":{"label":"TheGreatReview_","size":3,"x":54,"y":45,"c":4}},{"key":"8","attributes":{"label":"Drorian_","size":3,"x":-34,"y":80,"c":5}},{"key":"9","attributes":{"label":"Esban_","size":3,"x":-39,"y":13,"c":1}},{"key":"10","attributes":{"label":"iconoclaste_sp","size":3,"x":-20,"y":-42,"c":6}},{"key":"11","attributes":{"label":"SF_Sauroctone","size":3,"x":9,"y":-74,"c":0}},{"key":"12","attributes":{"label":"nicolasbchb","size":3,"x":7,"y":56,"c":4}},{"key":"13","attributes":{"label":"RevelateursFTV","size":3,"x":23,"y":-68,"c":7}},{"key":"14","attributes":{"label":"RailService","size":3,"x":52,"y":-63,"c":0}},{"key":"15","attributes":{"label":"Mousstery","size":5,"x":-26,"y":53,"c":5}},{"key":"16","attributes":{"label":"salomesaque","size":4,"x":-32,"y":-7,"c":8}},{"key":"17","attributes":{"label":"celeste_game","size":4,"x":-19,"y":23,"c":6}},{"key":"18","attributes":{"label":"SpotifyWeird","size":3,"x":-76,"y":40,"c":9}},{"key":"19","attributes":{"label":"Fransgenre","size":10,"x":-85,"y":-56,"c":1}},{"key":"20","attributes":{"label":"xymediafr","size":15,"x":-87,"y":-34,"c":1}},{"key":"21","attributes":{"label":"Mphala12","size":3,"x":-55,"y":-67,"c":1}},{"key":"22","attributes":{"label":"image_origins","size":6,"x":-67,"y":42,"c":5}},{"key":"23","attributes":{"label":"FallGuys_FR","size":3,"x":35,"y":86,"c":4}},{"key":"24","attributes":{"label":"LMPositif","size":3,"x":23,"y":57,"c":4}},{"key":"25","attributes":{"label":"JeannotNymouce","size":3,"x":49,"y":9,"c":0}},{"key":"26","attributes":{"label":"galacticamille","size":3,"x":-57,"y":26,"c":2}},{"key":"27","attributes":{"label":"greaby_","size":6,"x":16,"y":21,"c":6}},{"key":"28","attributes":{"label":"agit_prod","size":4,"x":-56,"y":-50,"c":1}},{"key":"29","attributes":{"label":"jack0tte_1","size":5,"x":-62,"y":-56,"c":1}},{"key":"30","attributes":{"label":"incelReplies","size":5,"x":-41,"y":47,"c":9}},{"key":"31","attributes":{"label":"wiki_trans","size":14,"x":-83,"y":-43,"c":1}},{"key":"32","attributes":{"label":"_RuneEva_","size":4,"x":25,"y":25,"c":6}},{"key":"33","attributes":{"label":"zizicaca_actu","size":4,"x":-18,"y":78,"c":5}},{"key":"34","attributes":{"label":"PlayGolfGang","size":3,"x":20,"y":83,"c":4}},{"key":"35","attributes":{"label":"depthsofwiki","size":14,"x":-52,"y":49,"c":5}},{"key":"36","attributes":{"label":"EbibiGlass","size":4,"x":-54,"y":-21,"c":3}},{"key":"37","attributes":{"label":"GoodReddit","size":5,"x":-80,"y":20,"c":9}},{"key":"38","attributes":{"label":"ClubPhotos_","size":3,"x":43,"y":37,"c":4}},{"key":"39","attributes":{"label":"Alopeksia","size":3,"x":25,"y":-37,"c":0}},{"key":"40","attributes":{"label":"lecoindeslgbt","size":15,"x":-74,"y":-29,"c":1}},{"key":"41","attributes":{"label":"OutOfBagHorty","size":4,"x":16,"y":44,"c":5}},{"key":"42","attributes":{"label":"GenetixVideos","size":7,"x":-76,"y":-56,"c":1}},{"key":"43","attributes":{"label":"OocHorty_","size":4,"x":-31,"y":66,"c":5}},{"key":"44","attributes":{"label":"BeaufDelphine","size":5,"x":-56,"y":55,"c":5}},{"key":"45","attributes":{"label":"COUPSURE","size":4,"x":31,"y":-69,"c":7}},{"key":"46","attributes":{"label":"L_ThinkTank","size":5,"x":-8,"y":-79,"c":7}},{"key":"47","attributes":{"label":"Owl__Kitty","size":3,"x":25,"y":31,"c":5}},{"key":"48","attributes":{"label":"Fact_N_Furious","size":3,"x":-50,"y":4,"c":2}},{"key":"49","attributes":{"label":"ChamboncelLea","size":4,"x":-52,"y":20,"c":2}},{"key":"50","attributes":{"label":"CoinersTakingLs","size":5,"x":-44,"y":49,"c":9}},{"key":"51","attributes":{"label":"ShapedInternet","size":5,"x":-64,"y":35,"c":9}},{"key":"52","attributes":{"label":"LaCherePoire","size":5,"x":-59,"y":-42,"c":1}},{"key":"53","attributes":{"label":"LoL_DFG","size":4,"x":34,"y":72,"c":4}},{"key":"54","attributes":{"label":"Feldup_official","size":11,"x":-9,"y":64,"c":5}},{"key":"55","attributes":{"label":"curiosiboite","size":3,"x":-21,"y":-68,"c":3}},{"key":"56","attributes":{"label":"Nirinine","size":5,"x":-45,"y":-74,"c":1}},{"key":"57","attributes":{"label":"kryssalian","size":4,"x":-20,"y":20,"c":6}},{"key":"58","attributes":{"label":"OPcrotte","size":4,"x":-60,"y":44,"c":5}},{"key":"59","attributes":{"label":"Copainduweb","size":4,"x":-13,"y":52,"c":5}},{"key":"60","attributes":{"label":"IndieMagFR","size":4,"x":31,"y":17,"c":6}},{"key":"61","attributes":{"label":"LuttiLutti_","size":4,"x":11,"y":72,"c":4}},{"key":"62","attributes":{"label":"PetitPiedDessin","size":3,"x":-33,"y":26,"c":4}},{"key":"63","attributes":{"label":"FbdnStories","size":4,"x":-2,"y":-74,"c":7}},{"key":"64","attributes":{"label":"morgane871","size":3,"x":8,"y":-39,"c":0}},{"key":"65","attributes":{"label":"regisRquoi","size":5,"x":16,"y":-74,"c":0}},{"key":"66","attributes":{"label":"slpng_giants_fr","size":5,"x":-66,"y":-17,"c":2}},{"key":"67","attributes":{"label":"tintinades","size":4,"x":-9,"y":30,"c":2}},{"key":"68","attributes":{"label":"ZLAN_FR","size":3,"x":25,"y":44,"c":4}},{"key":"69","attributes":{"label":"Xo_Trixy","size":4,"x":-25,"y":67,"c":5}},{"key":"70","attributes":{"label":"DiablePositif","size":5,"x":14,"y":-78,"c":0}},{"key":"71","attributes":{"label":"RpUnamed","size":5,"x":20,"y":-76,"c":0}},{"key":"72","attributes":{"label":"avamind_","size":4,"x":-10,"y":41,"c":4}},{"key":"73","attributes":{"label":"TheRightCant","size":3,"x":-53,"y":-16,"c":1}},{"key":"74","attributes":{"label":"Zulzoranderr","size":5,"x":-85,"y":8,"c":2}},{"key":"75","attributes":{"label":"HortyUnderscore","size":5,"x":-39,"y":54,"c":5}},{"key":"76","attributes":{"label":"Baghera__Jones","size":5,"x":-17,"y":65,"c":5}},{"key":"77","attributes":{"label":"XavDang","size":4,"x":8,"y":40,"c":2}},{"key":"78","attributes":{"label":"Eupholie_","size":5,"x":-41,"y":40,"c":5}},{"key":"79","attributes":{"label":"AfpFactuel","size":4,"x":36,"y":-26,"c":7}},{"key":"80","attributes":{"label":"jussetain","size":3,"x":-7,"y":57,"c":4}},{"key":"81","attributes":{"label":"pierrelapin","size":5,"x":-16,"y":83,"c":5}},{"key":"82","attributes":{"label":"MarieCPalot","size":5,"x":20,"y":74,"c":4}},{"key":"83","attributes":{"label":"bubuchenbois","size":5,"x":-68,"y":-39,"c":1}},{"key":"84","attributes":{"label":"PepperpotTeam","size":3,"x":60,"y":-14,"c":0}},{"key":"85","attributes":{"label":"Twitch","size":13,"x":66,"y":34,"c":4}},{"key":"86","attributes":{"label":"Xari_","size":4,"x":37,"y":71,"c":4}},{"key":"87","attributes":{"label":"Rivenzi_","size":4,"x":-5,"y":70,"c":4}},{"key":"88","attributes":{"label":"ultiaa","size":4,"x":-29,"y":71,"c":5}},{"key":"89","attributes":{"label":"Gom4rt_","size":3,"x":46,"y":63,"c":4}},{"key":"90","attributes":{"label":"Willvs","size":3,"x":20,"y":41,"c":4}},{"key":"91","attributes":{"label":"TwitchSupport","size":4,"x":30,"y":12,"c":6}},{"key":"92","attributes":{"label":"discord","size":3,"x":-56,"y":-13,"c":1}},{"key":"93","attributes":{"label":"wieselT","size":3,"x":-33,"y":32,"c":2}},{"key":"94","attributes":{"label":"LittleBigWhale","size":4,"x":-1,"y":41,"c":4}},{"key":"95","attributes":{"label":"DamDamOfficial","size":4,"x":-25,"y":22,"c":2}},{"key":"96","attributes":{"label":"RReichstadt","size":3,"x":-18,"y":-35,"c":8}},{"key":"97","attributes":{"label":"VieDeCarabin","size":5,"x":18,"y":-78,"c":0}},{"key":"98","attributes":{"label":"_Nat_Ali","size":4,"x":-61,"y":-19,"c":2}},{"key":"99","attributes":{"label":"Takamis_","size":3,"x":17,"y":-45,"c":0}},{"key":"100","attributes":{"label":"Titeuf","size":4,"x":-35,"y":66,"c":5}},{"key":"101","attributes":{"label":"AngleDroit_","size":6,"x":-33,"y":44,"c":5}},{"key":"102","attributes":{"label":"Nanarland","size":3,"x":52,"y":-16,"c":0}},{"key":"103","attributes":{"label":"DonaldDuckCover","size":3,"x":49,"y":-15,"c":0}},{"key":"104","attributes":{"label":"whatisalt236","size":9,"x":-15,"y":-23,"c":6}},{"key":"105","attributes":{"label":"JeanMassiet","size":4,"x":3,"y":30,"c":8}},{"key":"106","attributes":{"label":"chipzel","size":4,"x":-81,"y":1,"c":2}},{"key":"107","attributes":{"label":"xSqueeZie","size":5,"x":-1,"y":88,"c":5}},{"key":"108","attributes":{"label":"ArkeoToys","size":3,"x":52,"y":-27,"c":0}},{"key":"109","attributes":{"label":"IllumiReptilien","size":3,"x":21,"y":46,"c":4}},{"key":"110","attributes":{"label":"Ostpolitik","size":13,"x":-36,"y":-20,"c":1}},{"key":"111","attributes":{"label":"lucabobenrieth","size":3,"x":70,"y":2,"c":0}},{"key":"112","attributes":{"label":"RadisIrradie","size":3,"x":64,"y":0,"c":0}},{"key":"113","attributes":{"label":"TraduisonsLes","size":4,"x":-48,"y":29,"c":2}},{"key":"114","attributes":{"label":"Equipe1erDegre","size":5,"x":-16,"y":17,"c":4}},{"key":"115","attributes":{"label":"baborlelefan","size":4,"x":29,"y":55,"c":4}},{"key":"116","attributes":{"label":"decharlisons","size":3,"x":-21,"y":-63,"c":3}},{"key":"117","attributes":{"label":"prevensectes","size":3,"x":32,"y":-31,"c":0}},{"key":"118","attributes":{"label":"Marouch1196","size":3,"x":35,"y":-43,"c":0}},{"key":"119","attributes":{"label":"FVSP1","size":3,"x":7,"y":-42,"c":0}},{"key":"120","attributes":{"label":"Lamz_1020","size":3,"x":17,"y":-41,"c":0}},{"key":"121","attributes":{"label":"geckopic_bot","size":3,"x":24,"y":-48,"c":0}},{"key":"122","attributes":{"label":"SilmaeWolfess","size":3,"x":18,"y":-37,"c":0}},{"key":"123","attributes":{"label":"Mr_Ezorn","size":3,"x":13,"y":-46,"c":0}},{"key":"124","attributes":{"label":"katz_sx","size":3,"x":31,"y":-46,"c":0}},{"key":"125","attributes":{"label":"Kasu_Green","size":3,"x":29,"y":-35,"c":0}},{"key":"126","attributes":{"label":"VRCircle","size":3,"x":25,"y":-41,"c":0}},{"key":"127","attributes":{"label":"rift_info","size":3,"x":29,"y":-39,"c":0}},{"key":"128","attributes":{"label":"Maurice809","size":3,"x":25,"y":-33,"c":0}},{"key":"129","attributes":{"label":"Radin_ch","size":3,"x":21,"y":-40,"c":0}},{"key":"130","attributes":{"label":"Azaelle80","size":3,"x":16,"y":-48,"c":0}},{"key":"131","attributes":{"label":"regionduleman","size":3,"x":14,"y":-43,"c":0}},{"key":"132","attributes":{"label":"doctimatuer","size":3,"x":21,"y":-44,"c":0}},{"key":"133","attributes":{"label":"blogmisterhyde","size":3,"x":33,"y":-38,"c":0}},{"key":"134","attributes":{"label":"Im_not_Geek","size":3,"x":37,"y":-40,"c":0}},{"key":"135","attributes":{"label":"goupilapps","size":3,"x":27,"y":-47,"c":0}},{"key":"136","attributes":{"label":"cosplayeveryday","size":3,"x":36,"y":-33,"c":0}},{"key":"137","attributes":{"label":"Beuheu","size":3,"x":22,"y":-36,"c":0}},{"key":"138","attributes":{"label":"dr8bit","size":3,"x":12,"y":-40,"c":0}},{"key":"139","attributes":{"label":"HaDeSss","size":3,"x":28,"y":-43,"c":0}},{"key":"140","attributes":{"label":"poussykely","size":3,"x":37,"y":-36,"c":0}},{"key":"141","attributes":{"label":"saphirblanc","size":3,"x":15,"y":-38,"c":0}},{"key":"142","attributes":{"label":"Ronflexxx","size":3,"x":20,"y":-48,"c":0}},{"key":"143","attributes":{"label":"Sophiia_Melanie","size":3,"x":32,"y":-35,"c":0}},{"key":"144","attributes":{"label":"delainmusic","size":3,"x":10,"y":-44,"c":0}},{"key":"145","attributes":{"label":"Kaorrucos","size":3,"x":28,"y":-32,"c":0}},{"key":"146","attributes":{"label":"Pixeloutremer","size":3,"x":31,"y":-42,"c":0}},{"key":"147","attributes":{"label":"barrylopez","size":3,"x":24,"y":-44,"c":0}},{"key":"148","attributes":{"label":"FallGuysGame","size":3,"x":48,"y":65,"c":4}},{"key":"149","attributes":{"label":"TopDesAvis","size":3,"x":67,"y":-8,"c":0}},{"key":"150","attributes":{"label":"SamuelEtienne","size":5,"x":21,"y":35,"c":4}},{"key":"151","attributes":{"label":"Sabine_Quindou","size":5,"x":-1,"y":24,"c":4}},{"key":"152","attributes":{"label":"StopCovidApp","size":3,"x":-24,"y":-31,"c":8}},{"key":"153","attributes":{"label":"JulienPaniac","size":3,"x":-16,"y":36,"c":5}},{"key":"154","attributes":{"label":"Domingo","size":4,"x":7,"y":76,"c":4}},{"key":"155","attributes":{"label":"poncefleur","size":4,"x":11,"y":76,"c":4}},{"key":"156","attributes":{"label":"ZeratoR","size":5,"x":15,"y":82,"c":4}},{"key":"157","attributes":{"label":"l_extracteur","size":4,"x":-27,"y":-47,"c":3}},{"key":"158","attributes":{"label":"TwitchOOC","size":3,"x":47,"y":34,"c":4}},{"key":"159","attributes":{"label":"AREtoiles","size":5,"x":11,"y":84,"c":4}},{"key":"160","attributes":{"label":"Bolchefeuj","size":3,"x":-36,"y":-67,"c":1}},{"key":"161","attributes":{"label":"geoguessr","size":4,"x":-56,"y":-27,"c":2}},{"key":"162","attributes":{"label":"Gilles__Stella","size":4,"x":-36,"y":19,"c":2}},{"key":"163","attributes":{"label":"BakaBoo_","size":3,"x":-14,"y":33,"c":5}},{"key":"164","attributes":{"label":"BAG_OFSP_UFSP","size":13,"x":50,"y":-64,"c":0}},{"key":"165","attributes":{"label":"DomingoTV","size":3,"x":24,"y":41,"c":4}},{"key":"166","attributes":{"label":"MarxFanAccount","size":4,"x":-46,"y":-26,"c":2}},{"key":"167","attributes":{"label":"intrnetexp","size":3,"x":70,"y":-10,"c":0}},{"key":"168","attributes":{"label":"Guillaume_HB","size":4,"x":35,"y":-68,"c":7}},{"key":"169","attributes":{"label":"PepiteSexiste","size":6,"x":-54,"y":7,"c":1}},{"key":"170","attributes":{"label":"SpeeDonsFR","size":4,"x":-63,"y":-25,"c":2}},{"key":"171","attributes":{"label":"brutofficiel","size":3,"x":-53,"y":1,"c":2}},{"key":"172","attributes":{"label":"RemyBuisine","size":3,"x":-29,"y":19,"c":8}},{"key":"173","attributes":{"label":"T_Bouhafs","size":6,"x":-44,"y":-19,"c":1}},{"key":"174","attributes":{"label":"AllanBARTE","size":3,"x":-15,"y":-65,"c":3}},{"key":"175","attributes":{"label":"Crowdagger","size":4,"x":-49,"y":-35,"c":3}},{"key":"176","attributes":{"label":"Le_Stagirite","size":4,"x":-35,"y":-42,"c":8}},{"key":"177","attributes":{"label":"SciTania","size":4,"x":-6,"y":-47,"c":1}},{"key":"178","attributes":{"label":"ARTEfr","size":4,"x":-32,"y":-51,"c":8}},{"key":"179","attributes":{"label":"OutOfJDG","size":3,"x":67,"y":0,"c":0}},{"key":"180","attributes":{"label":"TerribleMaps","size":4,"x":-28,"y":37,"c":2}},{"key":"181","attributes":{"label":"LecordierB","size":3,"x":68,"y":-14,"c":0}},{"key":"182","attributes":{"label":"Loik_Bihan","size":3,"x":66,"y":4,"c":0}},{"key":"183","attributes":{"label":"ZEventfr","size":3,"x":-15,"y":40,"c":5}},{"key":"184","attributes":{"label":"LUppsala","size":5,"x":-51,"y":-62,"c":1}},{"key":"185","attributes":{"label":"pandovstrochnis","size":5,"x":-68,"y":-31,"c":1}},{"key":"186","attributes":{"label":"tuCpakoa","size":3,"x":-23,"y":33,"c":5}},{"key":"187","attributes":{"label":"Simon_Puech","size":4,"x":-19,"y":32,"c":8}},{"key":"188","attributes":{"label":"charlesvillaa","size":3,"x":-22,"y":-28,"c":8}},{"key":"189","attributes":{"label":"Melusine_2","size":5,"x":-61,"y":3,"c":1}},{"key":"190","attributes":{"label":"amnestyfrance","size":3,"x":-19,"y":-31,"c":8}},{"key":"191","attributes":{"label":"Micode","size":3,"x":25,"y":48,"c":4}},{"key":"192","attributes":{"label":"PAUL_videos","size":3,"x":50,"y":-11,"c":0}},{"key":"193","attributes":{"label":"stupidites","size":4,"x":-27,"y":-74,"c":1}},{"key":"194","attributes":{"label":"GretaThunberg","size":4,"x":-45,"y":24,"c":8}},{"key":"195","attributes":{"label":"RespectfulMemes","size":4,"x":6,"y":34,"c":2}},{"key":"196","attributes":{"label":"SkeptikonFR","size":3,"x":-43,"y":15,"c":2}},{"key":"197","attributes":{"label":"Bouletcorp","size":3,"x":-48,"y":1,"c":2}},{"key":"198","attributes":{"label":"ScienceClic","size":3,"x":28,"y":47,"c":4}},{"key":"199","attributes":{"label":"mamytwink","size":4,"x":-48,"y":40,"c":2}},{"key":"200","attributes":{"label":"Bolchegeek","size":5,"x":-40,"y":-30,"c":1}},{"key":"201","attributes":{"label":"un_creatif","size":4,"x":11,"y":24,"c":8}},{"key":"202","attributes":{"label":"TontonDukteef","size":3,"x":-34,"y":-64,"c":1}},{"key":"203","attributes":{"label":"At0mium_","size":6,"x":49,"y":50,"c":4}},{"key":"204","attributes":{"label":"botchvideos","size":3,"x":59,"y":-29,"c":0}},{"key":"205","attributes":{"label":"CopyComicVideos","size":3,"x":74,"y":1,"c":0}},{"key":"206","attributes":{"label":"i_nebuleuse","size":3,"x":-32,"y":-68,"c":1}},{"key":"207","attributes":{"label":"PuNkY_YT","size":3,"x":55,"y":-29,"c":0}},{"key":"208","attributes":{"label":"THEMisterfox","size":3,"x":54,"y":-23,"c":0}},{"key":"209","attributes":{"label":"Sheshounet","size":4,"x":60,"y":46,"c":4}},{"key":"210","attributes":{"label":"LeBjrTristesse","size":3,"x":-10,"y":23,"c":8}},{"key":"211","attributes":{"label":"JBS_Ibonek","size":4,"x":35,"y":67,"c":4}},{"key":"212","attributes":{"label":"Passage004","size":4,"x":36,"y":61,"c":4}},{"key":"213","attributes":{"label":"Mad_Chien","size":3,"x":29,"y":33,"c":5}},{"key":"214","attributes":{"label":"decentralises","size":3,"x":30,"y":29,"c":5}},{"key":"215","attributes":{"label":"Mehdi_Moussaid","size":4,"x":39,"y":33,"c":6}},{"key":"216","attributes":{"label":"Cestpassorcier","size":3,"x":-42,"y":19,"c":2}},{"key":"217","attributes":{"label":"CyrusNorth","size":3,"x":47,"y":38,"c":4}},{"key":"218","attributes":{"label":"PaleonewsFrance","size":3,"x":-46,"y":14,"c":2}},{"key":"219","attributes":{"label":"gourmaud_jamy","size":3,"x":44,"y":33,"c":4}},{"key":"220","attributes":{"label":"Asclepios_YT","size":3,"x":61,"y":-10,"c":0}},{"key":"221","attributes":{"label":"FAKE_Investiga","size":4,"x":36,"y":-23,"c":7}},{"key":"222","attributes":{"label":"OLGuillemets","size":5,"x":-40,"y":4,"c":1}},{"key":"223","attributes":{"label":"revuesdumonde","size":4,"x":0,"y":33,"c":8}},{"key":"224","attributes":{"label":"_dieuoff","size":3,"x":70,"y":-6,"c":0}},{"key":"225","attributes":{"label":"1DropDansLaMare","size":3,"x":70,"y":-18,"c":0}},{"key":"226","attributes":{"label":"MonsieurPlouf","size":3,"x":73,"y":6,"c":0}},{"key":"227","attributes":{"label":"ChatSceptique","size":3,"x":60,"y":-5,"c":0}},{"key":"228","attributes":{"label":"LeSadPanda","size":3,"x":65,"y":-20,"c":0}},{"key":"229","attributes":{"label":"Jirayalecochon","size":4,"x":30,"y":72,"c":4}},{"key":"230","attributes":{"label":"MenuManga","size":3,"x":60,"y":-25,"c":0}},{"key":"231","attributes":{"label":"ManonBrilCUAH","size":4,"x":-34,"y":12,"c":8}},{"key":"232","attributes":{"label":"Numerama","size":3,"x":-12,"y":36,"c":5}},{"key":"233","attributes":{"label":"Evidencebbh","size":3,"x":9,"y":-52,"c":3}},{"key":"234","attributes":{"label":"HugoTravers","size":3,"x":-6,"y":53,"c":4}},{"key":"235","attributes":{"label":"BaladeMentale","size":3,"x":32,"y":-18,"c":8}},{"key":"236","attributes":{"label":"LCosmique","size":3,"x":72,"y":-14,"c":0}},{"key":"237","attributes":{"label":"TeleCrayon","size":4,"x":-46,"y":-31,"c":2}},{"key":"238","attributes":{"label":"Shadow_France","size":3,"x":16,"y":40,"c":4}},{"key":"239","attributes":{"label":"JulienChieze","size":4,"x":31,"y":68,"c":4}},{"key":"240","attributes":{"label":"ComplotsFaciles","size":6,"x":29,"y":43,"c":6}},{"key":"241","attributes":{"label":"RaAaKtheFox","size":3,"x":63,"y":-7,"c":0}},{"key":"242","attributes":{"label":"conspiration","size":4,"x":29,"y":-73,"c":7}},{"key":"243","attributes":{"label":"Kulturemoi","size":3,"x":62,"y":-18,"c":0}},{"key":"244","attributes":{"label":"DeBunKerEtoiles","size":4,"x":33,"y":-72,"c":7}},{"key":"245","attributes":{"label":"Stupid_Eco","size":4,"x":-8,"y":-40,"c":3}},{"key":"246","attributes":{"label":"Acermendax","size":3,"x":64,"y":-15,"c":0}},{"key":"247","attributes":{"label":"Chronique_NEXUS","size":4,"x":56,"y":23,"c":6}},{"key":"248","attributes":{"label":"PetitAstronome","size":4,"x":-30,"y":-74,"c":1}},{"key":"249","attributes":{"label":"nanofictions","size":4,"x":-45,"y":8,"c":6}},{"key":"250","attributes":{"label":"BaladoSC","size":3,"x":-18,"y":-65,"c":3}},{"key":"251","attributes":{"label":"ConfdHistoire","size":3,"x":54,"y":-8,"c":0}},{"key":"252","attributes":{"label":"Aienkei","size":3,"x":67,"y":8,"c":0}},{"key":"253","attributes":{"label":"HorionManga","size":3,"x":67,"y":-17,"c":0}},{"key":"254","attributes":{"label":"xychelsea","size":6,"x":-80,"y":-27,"c":2}},{"key":"255","attributes":{"label":"ChaykaHackso","size":6,"x":-30,"y":-62,"c":1}},{"key":"256","attributes":{"label":"DanyCaligula","size":6,"x":-41,"y":-46,"c":1}},{"key":"257","attributes":{"label":"hackingsocialfr","size":3,"x":6,"y":-50,"c":3}},{"key":"258","attributes":{"label":"Scilabus","size":3,"x":54,"y":-19,"c":0}},{"key":"259","attributes":{"label":"WTFake_","size":3,"x":54,"y":-12,"c":0}},{"key":"260","attributes":{"label":"bbcdoctorwho","size":6,"x":61,"y":23,"c":6}},{"key":"261","attributes":{"label":"DEFAKATOR_Off","size":4,"x":5,"y":12,"c":7}},{"key":"262","attributes":{"label":"ErmiteModerne","size":3,"x":57,"y":-7,"c":0}},{"key":"263","attributes":{"label":"LeoTechMaker","size":3,"x":50,"y":62,"c":4}},{"key":"264","attributes":{"label":"Cyril_mp4","size":4,"x":39,"y":67,"c":4}},{"key":"265","attributes":{"label":"PlayOverwatch","size":3,"x":-19,"y":39,"c":5}},{"key":"266","attributes":{"label":"FrancoisTheurel","size":3,"x":33,"y":-14,"c":8}},{"key":"267","attributes":{"label":"RoiLennon","size":4,"x":48,"y":55,"c":4}},{"key":"268","attributes":{"label":"Bunker_D_","size":4,"x":-40,"y":-72,"c":3}},{"key":"269","attributes":{"label":"UnGarage","size":3,"x":-18,"y":-61,"c":3}},{"key":"270","attributes":{"label":"framasoft","size":4,"x":-3,"y":-46,"c":1}},{"key":"271","attributes":{"label":"leroidesrats","size":3,"x":-22,"y":-34,"c":8}},{"key":"272","attributes":{"label":"MisterJDay","size":3,"x":50,"y":-19,"c":0}},{"key":"273","attributes":{"label":"neiltyson","size":3,"x":-51,"y":-2,"c":2}},{"key":"274","attributes":{"label":"CinemaDurendal","size":3,"x":62,"y":-3,"c":0}},{"key":"275","attributes":{"label":"FlorencePorcel","size":4,"x":-21,"y":2,"c":8}},{"key":"276","attributes":{"label":"malaisetele","size":3,"x":58,"y":-22,"c":0}},{"key":"277","attributes":{"label":"legrandjd","size":4,"x":-45,"y":57,"c":2}},{"key":"278","attributes":{"label":"DChandelier","size":4,"x":-83,"y":-2,"c":2}},{"key":"279","attributes":{"label":"DaveFoShizzle","size":3,"x":32,"y":-9,"c":8}},{"key":"280","attributes":{"label":"ParlonsYstoire","size":3,"x":56,"y":-26,"c":0}},{"key":"281","attributes":{"label":"AAstierOff","size":3,"x":-12,"y":10,"c":2}},{"key":"282","attributes":{"label":"VledTapas","size":3,"x":58,"y":-18,"c":0}},{"key":"283","attributes":{"label":"HygieneMentale","size":4,"x":-2,"y":-50,"c":1}},{"key":"284","attributes":{"label":"TroncheBiais","size":3,"x":63,"y":-27,"c":0}},{"key":"285","attributes":{"label":"patrick_baud","size":5,"x":33,"y":40,"c":6}},{"key":"286","attributes":{"label":"didichandouidou","size":3,"x":69,"y":12,"c":0}},{"key":"287","attributes":{"label":"epenser","size":3,"x":51,"y":36,"c":4}},{"key":"288","attributes":{"label":"Taupe10videos","size":3,"x":57,"y":-11,"c":0}},{"key":"289","attributes":{"label":"NotaBeneMovies","size":3,"x":69,"y":-21,"c":0}},{"key":"290","attributes":{"label":"Linguisticae","size":3,"x":50,"y":-23,"c":0}},{"key":"291","attributes":{"label":"superflameur","size":4,"x":34,"y":46,"c":5}},{"key":"292","attributes":{"label":"NoMansSky","size":4,"x":28,"y":15,"c":6}},{"key":"293","attributes":{"label":"Sale_Con","size":4,"x":-49,"y":-6,"c":8}},{"key":"294","attributes":{"label":"KraynJV","size":4,"x":52,"y":24,"c":6}},{"key":"295","attributes":{"label":"PeterMolydeux","size":4,"x":-60,"y":-29,"c":2}},{"key":"296","attributes":{"label":"Ganeshdeux","size":3,"x":66,"y":-4,"c":0}},{"key":"297","attributes":{"label":"le_gorafi","size":3,"x":20,"y":30,"c":5}},{"key":"298","attributes":{"label":"GamesDoneQuick","size":4,"x":-59,"y":-25,"c":2}},{"key":"299","attributes":{"label":"DieuOfficiel","size":3,"x":56,"y":-15,"c":0}},{"key":"300","attributes":{"label":"Meeea","size":3,"x":69,"y":5,"c":0}},{"key":"301","attributes":{"label":"mistermv","size":6,"x":17,"y":68,"c":5}},{"key":"302","attributes":{"label":"pcgamer","size":3,"x":-21,"y":37,"c":5}},{"key":"303","attributes":{"label":"Raph_Descraques","size":4,"x":-2,"y":18,"c":2}},{"key":"304","attributes":{"label":"RealMyop","size":3,"x":-9,"y":13,"c":2}},{"key":"305","attributes":{"label":"Benzaie_tgwtg","size":3,"x":66,"y":-24,"c":0}},{"key":"306","attributes":{"label":"memepastredrole","size":3,"x":74,"y":-3,"c":0}},{"key":"307","attributes":{"label":"Mathieu_Sommet","size":3,"x":73,"y":-11,"c":0}},{"key":"308","attributes":{"label":"UsulduFutur","size":6,"x":-44,"y":-13,"c":1}},{"key":"309","attributes":{"label":"MrAntoineDaniel","size":6,"x":-1,"y":65,"c":4}},{"key":"310","attributes":{"label":"Klaire","size":4,"x":-69,"y":26,"c":2}},{"key":"311","attributes":{"label":"Seb_du_Grenier","size":3,"x":-14,"y":8,"c":2}},{"key":"312","attributes":{"label":"Frederic_Molas","size":5,"x":41,"y":54,"c":4}},{"key":"313","attributes":{"label":"Calimaq","size":3,"x":71,"y":9,"c":0}},{"key":"314","attributes":{"label":"Alttpweek","size":4,"x":-57,"y":-31,"c":2}},{"key":"315","attributes":{"label":"Marcuszeboulet","size":3,"x":71,"y":-2,"c":0}},{"key":"316","attributes":{"label":"F_Descraques","size":3,"x":74,"y":-7,"c":0}},{"key":"317","attributes":{"label":"brainmagazine","size":3,"x":-54,"y":-3,"c":2}},{"key":"318","attributes":{"label":"bastamedia_","size":3,"x":-17,"y":-68,"c":3}},{"key":"319","attributes":{"label":"LOLannonces","size":3,"x":65,"y":-11,"c":0}},{"key":"320","attributes":{"label":"Korben","size":4,"x":46,"y":24,"c":6}},{"key":"321","attributes":{"label":"FrMinecraft","size":3,"x":-45,"y":18,"c":2}},{"key":"322","attributes":{"label":"laquadrature","size":5,"x":-28,"y":-24,"c":1}},{"key":"323","attributes":{"label":"4chan","size":3,"x":62,"y":-22,"c":0}}],"edges":[{"key":"324","source":"0","target":"1"},{"key":"325","source":"0","target":"2"},{"key":"326","source":"0","target":"3"},{"key":"327","source":"0","target":"4"},{"key":"328","source":"0","target":"5"},{"key":"329","source":"0","target":"6"},{"key":"330","source":"0","target":"7"},{"key":"331","source":"0","target":"8"},{"key":"332","source":"0","target":"9"},{"key":"333","source":"0","target":"10"},{"key":"334","source":"0","target":"11"},{"key":"335","source":"0","target":"12"},{"key":"336","source":"0","target":"13"},{"key":"337","source":"0","target":"14"},{"key":"338","source":"0","target":"15"},{"key":"339","source":"0","target":"16"},{"key":"340","source":"0","target":"17"},{"key":"341","source":"0","target":"18"},{"key":"342","source":"0","target":"19"},{"key":"343","source":"0","target":"20"},{"key":"344","source":"0","target":"21"},{"key":"345","source":"0","target":"22"},{"key":"346","source":"0","target":"23"},{"key":"347","source":"0","target":"24"},{"key":"348","source":"0","target":"25"},{"key":"349","source":"0","target":"26"},{"key":"350","source":"0","target":"27"},{"key":"351","source":"0","target":"28"},{"key":"352","source":"0","target":"29"},{"key":"353","source":"0","target":"30"},{"key":"354","source":"0","target":"31"},{"key":"355","source":"0","target":"32"},{"key":"356","source":"0","target":"33"},{"key":"357","source":"0","target":"34"},{"key":"358","source":"0","target":"35"},{"key":"359","source":"0","target":"36"},{"key":"360","source":"0","target":"37"},{"key":"361","source":"0","target":"38"},{"key":"362","source":"0","target":"39"},{"key":"363","source":"0","target":"40"},{"key":"364","source":"0","target":"41"},{"key":"365","source":"0","target":"42"},{"key":"366","source":"0","target":"43"},{"key":"367","source":"0","target":"44"},{"key":"368","source":"0","target":"45"},{"key":"369","source":"0","target":"46"},{"key":"370","source":"0","target":"47"},{"key":"371","source":"0","target":"48"},{"key":"372","source":"0","target":"49"},{"key":"373","source":"0","target":"50"},{"key":"374","source":"0","target":"51"},{"key":"375","source":"0","target":"52"},{"key":"376","source":"0","target":"53"},{"key":"377","source":"0","target":"54"},{"key":"378","source":"0","target":"55"},{"key":"379","source":"0","target":"56"},{"key":"380","source":"0","target":"57"},{"key":"381","source":"0","target":"58"},{"key":"382","source":"0","target":"59"},{"key":"383","source":"0","target":"60"},{"key":"384","source":"0","target":"61"},{"key":"385","source":"0","target":"62"},{"key":"386","source":"0","target":"63"},{"key":"387","source":"0","target":"64"},{"key":"388","source":"0","target":"65"},{"key":"389","source":"0","target":"66"},{"key":"390","source":"0","target":"67"},{"key":"391","source":"0","target":"68"},{"key":"392","source":"0","target":"69"},{"key":"393","source":"0","target":"70"},{"key":"394","source":"0","target":"71"},{"key":"395","source":"0","target":"72"},{"key":"396","source":"0","target":"73"},{"key":"397","source":"0","target":"74"},{"key":"398","source":"0","target":"75"},{"key":"399","source":"0","target":"76"},{"key":"400","source":"0","target":"77"},{"key":"401","source":"0","target":"78"},{"key":"402","source":"0","target":"79"},{"key":"403","source":"0","target":"80"},{"key":"404","source":"0","target":"81"},{"key":"405","source":"0","target":"82"},{"key":"406","source":"0","target":"83"},{"key":"407","source":"0","target":"84"},{"key":"408","source":"0","target":"85"},{"key":"409","source":"0","target":"86"},{"key":"410","source":"0","target":"87"},{"key":"411","source":"0","target":"88"},{"key":"412","source":"0","target":"89"},{"key":"413","source":"0","target":"90"},{"key":"414","source":"0","target":"91"},{"key":"415","source":"0","target":"92"},{"key":"416","source":"0","target":"93"},{"key":"417","source":"0","target":"94"},{"key":"418","source":"0","target":"95"},{"key":"419","source":"0","target":"96"},{"key":"420","source":"0","target":"97"},{"key":"421","source":"0","target":"98"},{"key":"422","source":"0","target":"99"},{"key":"423","source":"0","target":"100"},{"key":"424","source":"0","target":"101"},{"key":"425","source":"0","target":"102"},{"key":"426","source":"0","target":"103"},{"key":"427","source":"0","target":"104"},{"key":"428","source":"0","target":"105"},{"key":"429","source":"0","target":"106"},{"key":"430","source":"0","target":"107"},{"key":"431","source":"0","target":"108"},{"key":"432","source":"0","target":"109"},{"key":"433","source":"0","target":"110"},{"key":"434","source":"0","target":"111"},{"key":"435","source":"0","target":"112"},{"key":"436","source":"0","target":"113"},{"key":"437","source":"0","target":"114"},{"key":"438","source":"0","target":"115"},{"key":"439","source":"0","target":"116"},{"key":"440","source":"11","target":"0"},{"key":"441","source":"21","target":"0"},{"key":"442","source":"27","target":"0"},{"key":"443","source":"32","target":"0"},{"key":"444","source":"39","target":"0"},{"key":"445","source":"64","target":"0"},{"key":"446","source":"99","target":"0"},{"key":"447","source":"117","target":"0"},{"key":"448","source":"118","target":"0"},{"key":"449","source":"119","target":"0"},{"key":"450","source":"120","target":"0"},{"key":"451","source":"121","target":"0"},{"key":"452","source":"122","target":"0"},{"key":"453","source":"123","target":"0"},{"key":"454","source":"124","target":"0"},{"key":"455","source":"125","target":"0"},{"key":"456","source":"126","target":"0"},{"key":"457","source":"127","target":"0"},{"key":"458","source":"128","target":"0"},{"key":"459","source":"129","target":"0"},{"key":"460","source":"130","target":"0"},{"key":"461","source":"131","target":"0"},{"key":"462","source":"132","target":"0"},{"key":"463","source":"133","target":"0"},{"key":"464","source":"134","target":"0"},{"key":"465","source":"135","target":"0"},{"key":"466","source":"136","target":"0"},{"key":"467","source":"137","target":"0"},{"key":"468","source":"138","target":"0"},{"key":"469","source":"139","target":"0"},{"key":"470","source":"140","target":"0"},{"key":"471","source":"141","target":"0"},{"key":"472","source":"142","target":"0"},{"key":"473","source":"143","target":"0"},{"key":"474","source":"144","target":"0"},{"key":"475","source":"145","target":"0"},{"key":"476","source":"146","target":"0"},{"key":"477","source":"147","target":"0"},{"key":"478","source":"1","target":"74"},{"key":"479","source":"1","target":"113"},{"key":"480","source":"1","target":"2"},{"key":"481","source":"1","target":"3"},{"key":"482","source":"1","target":"18"},{"key":"483","source":"1","target":"28"},{"key":"484","source":"1","target":"75"},{"key":"485","source":"1","target":"37"},{"key":"486","source":"1","target":"58"},{"key":"487","source":"2","target":"19"},{"key":"488","source":"2","target":"40"},{"key":"489","source":"2","target":"42"},{"key":"490","source":"2","target":"31"},{"key":"491","source":"2","target":"20"},{"key":"492","source":"3","target":"1"},{"key":"493","source":"3","target":"49"},{"key":"494","source":"3","target":"26"},{"key":"495","source":"3","target":"48"},{"key":"496","source":"3","target":"5"},{"key":"497","source":"3","target":"58"},{"key":"498","source":"3","target":"29"},{"key":"499","source":"3","target":"83"},{"key":"500","source":"3","target":"59"},{"key":"501","source":"4","target":"98"},{"key":"502","source":"5","target":"3"},{"key":"503","source":"5","target":"66"},{"key":"504","source":"5","target":"20"},{"key":"505","source":"7","target":"85"},{"key":"506","source":"8","target":"69"},{"key":"507","source":"8","target":"59"},{"key":"508","source":"8","target":"78"},{"key":"509","source":"8","target":"44"},{"key":"510","source":"8","target":"101"},{"key":"511","source":"8","target":"100"},{"key":"512","source":"8","target":"33"},{"key":"513","source":"8","target":"43"},{"key":"514","source":"8","target":"41"},{"key":"515","source":"8","target":"88"},{"key":"516","source":"8","target":"54"},{"key":"517","source":"8","target":"81"},{"key":"518","source":"8","target":"58"},{"key":"519","source":"8","target":"15"},{"key":"520","source":"8","target":"72"},{"key":"521","source":"8","target":"87"},{"key":"522","source":"8","target":"76"},{"key":"523","source":"8","target":"75"},{"key":"524","source":"8","target":"107"},{"key":"525","source":"9","target":"54"},{"key":"526","source":"9","target":"40"},{"key":"527","source":"10","target":"110"},{"key":"528","source":"10","target":"104"},{"key":"529","source":"11","target":"110"},{"key":"530","source":"11","target":"71"},{"key":"531","source":"11","target":"97"},{"key":"532","source":"11","target":"70"},{"key":"533","source":"12","target":"50"},{"key":"534","source":"12","target":"30"},{"key":"535","source":"12","target":"7"},{"key":"536","source":"12","target":"76"},{"key":"537","source":"12","target":"27"},{"key":"538","source":"12","target":"38"},{"key":"539","source":"12","target":"78"},{"key":"540","source":"12","target":"53"},{"key":"541","source":"12","target":"15"},{"key":"542","source":"12","target":"90"},{"key":"543","source":"12","target":"49"},{"key":"544","source":"0","target":"148"},{"key":"545","source":"0","target":"149"},{"key":"546","source":"0","target":"118"},{"key":"547","source":"0","target":"150"},{"key":"548","source":"0","target":"151"},{"key":"549","source":"0","target":"152"},{"key":"550","source":"0","target":"153"},{"key":"551","source":"0","target":"154"},{"key":"552","source":"0","target":"155"},{"key":"553","source":"0","target":"156"},{"key":"554","source":"0","target":"157"},{"key":"555","source":"0","target":"158"},{"key":"556","source":"0","target":"159"},{"key":"557","source":"0","target":"160"},{"key":"558","source":"0","target":"161"},{"key":"559","source":"0","target":"162"},{"key":"560","source":"0","target":"163"},{"key":"561","source":"0","target":"164"},{"key":"562","source":"0","target":"165"},{"key":"563","source":"0","target":"166"},{"key":"564","source":"0","target":"167"},{"key":"565","source":"0","target":"168"},{"key":"566","source":"0","target":"169"},{"key":"567","source":"0","target":"170"},{"key":"568","source":"0","target":"171"},{"key":"569","source":"0","target":"172"},{"key":"570","source":"0","target":"173"},{"key":"571","source":"0","target":"174"},{"key":"572","source":"0","target":"175"},{"key":"573","source":"0","target":"176"},{"key":"574","source":"0","target":"177"},{"key":"575","source":"0","target":"178"},{"key":"576","source":"0","target":"179"},{"key":"577","source":"0","target":"180"},{"key":"578","source":"0","target":"181"},{"key":"579","source":"0","target":"182"},{"key":"580","source":"0","target":"183"},{"key":"581","source":"0","target":"184"},{"key":"582","source":"0","target":"117"},{"key":"583","source":"0","target":"185"},{"key":"584","source":"0","target":"186"},{"key":"585","source":"0","target":"187"},{"key":"586","source":"0","target":"188"},{"key":"587","source":"0","target":"189"},{"key":"588","source":"0","target":"190"},{"key":"589","source":"0","target":"191"},{"key":"590","source":"0","target":"192"},{"key":"591","source":"0","target":"193"},{"key":"592","source":"0","target":"194"},{"key":"593","source":"0","target":"195"},{"key":"594","source":"0","target":"196"},{"key":"595","source":"0","target":"197"},{"key":"596","source":"0","target":"198"},{"key":"597","source":"0","target":"199"},{"key":"598","source":"0","target":"200"},{"key":"599","source":"0","target":"201"},{"key":"600","source":"0","target":"202"},{"key":"601","source":"0","target":"203"},{"key":"602","source":"0","target":"204"},{"key":"603","source":"0","target":"205"},{"key":"604","source":"0","target":"206"},{"key":"605","source":"0","target":"207"},{"key":"606","source":"0","target":"208"},{"key":"607","source":"0","target":"209"},{"key":"608","source":"0","target":"210"},{"key":"609","source":"0","target":"211"},{"key":"610","source":"0","target":"212"},{"key":"611","source":"0","target":"213"},{"key":"612","source":"0","target":"214"},{"key":"613","source":"0","target":"215"},{"key":"614","source":"0","target":"216"},{"key":"615","source":"0","target":"217"},{"key":"616","source":"0","target":"218"},{"key":"617","source":"0","target":"219"},{"key":"618","source":"0","target":"220"},{"key":"619","source":"0","target":"221"},{"key":"620","source":"0","target":"222"},{"key":"621","source":"0","target":"223"},{"key":"622","source":"0","target":"224"},{"key":"623","source":"1","target":"83"},{"key":"624","source":"1","target":"22"},{"key":"625","source":"1","target":"173"},{"key":"626","source":"1","target":"40"},{"key":"627","source":"1","target":"92"},{"key":"628","source":"1","target":"21"},{"key":"629","source":"1","target":"94"},{"key":"630","source":"1","target":"62"},{"key":"631","source":"1","target":"44"},{"key":"632","source":"1","target":"29"},{"key":"633","source":"1","target":"95"},{"key":"634","source":"1","target":"72"},{"key":"635","source":"1","target":"33"},{"key":"636","source":"1","target":"49"},{"key":"637","source":"3","target":"20"},{"key":"638","source":"3","target":"76"},{"key":"639","source":"3","target":"88"},{"key":"640","source":"3","target":"101"},{"key":"641","source":"3","target":"16"},{"key":"642","source":"3","target":"74"},{"key":"643","source":"3","target":"36"},{"key":"644","source":"3","target":"106"},{"key":"645","source":"3","target":"78"},{"key":"646","source":"3","target":"44"},{"key":"647","source":"3","target":"185"},{"key":"648","source":"3","target":"95"},{"key":"649","source":"4","target":"174"},{"key":"650","source":"4","target":"15"},{"key":"651","source":"4","target":"55"},{"key":"652","source":"5","target":"106"},{"key":"653","source":"5","target":"78"},{"key":"654","source":"5","target":"161"},{"key":"655","source":"5","target":"31"},{"key":"656","source":"5","target":"170"},{"key":"657","source":"11","target":"65"},{"key":"658","source":"12","target":"80"},{"key":"659","source":"12","target":"16"},{"key":"660","source":"12","target":"95"},{"key":"661","source":"12","target":"223"},{"key":"662","source":"12","target":"72"},{"key":"663","source":"12","target":"187"},{"key":"664","source":"12","target":"66"},{"key":"665","source":"12","target":"82"},{"key":"666","source":"12","target":"59"},{"key":"667","source":"12","target":"77"},{"key":"668","source":"12","target":"86"},{"key":"669","source":"12","target":"62"},{"key":"670","source":"12","target":"191"},{"key":"671","source":"12","target":"87"},{"key":"672","source":"12","target":"211"},{"key":"673","source":"13","target":"46"},{"key":"674","source":"13","target":"45"},{"key":"675","source":"14","target":"164"},{"key":"676","source":"15","target":"8"},{"key":"677","source":"15","target":"33"},{"key":"678","source":"15","target":"213"},{"key":"679","source":"15","target":"35"},{"key":"680","source":"15","target":"47"},{"key":"681","source":"15","target":"105"},{"key":"682","source":"15","target":"22"},{"key":"683","source":"15","target":"59"},{"key":"684","source":"15","target":"154"},{"key":"685","source":"15","target":"80"},{"key":"686","source":"15","target":"169"},{"key":"687","source":"15","target":"163"},{"key":"688","source":"15","target":"214"},{"key":"689","source":"15","target":"88"},{"key":"690","source":"15","target":"44"},{"key":"691","source":"15","target":"101"},{"key":"692","source":"15","target":"159"},{"key":"693","source":"15","target":"67"},{"key":"694","source":"15","target":"75"},{"key":"695","source":"16","target":"4"},{"key":"696","source":"16","target":"96"},{"key":"697","source":"16","target":"157"},{"key":"698","source":"18","target":"22"},{"key":"699","source":"18","target":"50"},{"key":"700","source":"18","target":"30"},{"key":"701","source":"18","target":"37"},{"key":"702","source":"19","target":"20"},{"key":"703","source":"19","target":"31"},{"key":"704","source":"0","target":"225"},{"key":"705","source":"0","target":"226"},{"key":"706","source":"0","target":"227"},{"key":"707","source":"0","target":"228"},{"key":"708","source":"0","target":"229"},{"key":"709","source":"0","target":"230"},{"key":"710","source":"0","target":"231"},{"key":"711","source":"0","target":"232"},{"key":"712","source":"0","target":"233"},{"key":"713","source":"0","target":"234"},{"key":"714","source":"0","target":"235"},{"key":"715","source":"0","target":"119"},{"key":"716","source":"0","target":"236"},{"key":"717","source":"0","target":"237"},{"key":"718","source":"0","target":"238"},{"key":"719","source":"0","target":"143"},{"key":"720","source":"0","target":"239"},{"key":"721","source":"0","target":"240"},{"key":"722","source":"0","target":"241"},{"key":"723","source":"0","target":"242"},{"key":"724","source":"0","target":"243"},{"key":"725","source":"0","target":"244"},{"key":"726","source":"0","target":"245"},{"key":"727","source":"0","target":"246"},{"key":"728","source":"0","target":"120"},{"key":"729","source":"0","target":"247"},{"key":"730","source":"0","target":"248"},{"key":"731","source":"0","target":"249"},{"key":"732","source":"0","target":"250"},{"key":"733","source":"0","target":"251"},{"key":"734","source":"0","target":"252"},{"key":"735","source":"0","target":"253"},{"key":"736","source":"0","target":"254"},{"key":"737","source":"0","target":"255"},{"key":"738","source":"0","target":"256"},{"key":"739","source":"0","target":"257"},{"key":"740","source":"0","target":"258"},{"key":"741","source":"0","target":"259"},{"key":"742","source":"0","target":"260"},{"key":"743","source":"0","target":"261"},{"key":"744","source":"0","target":"121"},{"key":"745","source":"0","target":"262"},{"key":"746","source":"0","target":"263"},{"key":"747","source":"0","target":"264"},{"key":"748","source":"0","target":"265"},{"key":"749","source":"0","target":"266"},{"key":"750","source":"0","target":"267"},{"key":"751","source":"0","target":"268"},{"key":"752","source":"0","target":"122"},{"key":"753","source":"1","target":"19"},{"key":"754","source":"1","target":"98"},{"key":"755","source":"1","target":"15"},{"key":"756","source":"1","target":"66"},{"key":"757","source":"1","target":"16"},{"key":"758","source":"1","target":"256"},{"key":"759","source":"1","target":"31"},{"key":"760","source":"1","target":"222"},{"key":"761","source":"1","target":"101"},{"key":"762","source":"1","target":"20"},{"key":"763","source":"1","target":"73"},{"key":"764","source":"1","target":"231"},{"key":"765","source":"1","target":"200"},{"key":"766","source":"1","target":"110"},{"key":"767","source":"1","target":"249"},{"key":"768","source":"3","target":"261"},{"key":"769","source":"3","target":"175"},{"key":"770","source":"3","target":"194"},{"key":"771","source":"3","target":"189"},{"key":"772","source":"4","target":"245"},{"key":"773","source":"4","target":"40"},{"key":"774","source":"4","target":"268"},{"key":"775","source":"4","target":"237"},{"key":"776","source":"4","target":"233"},{"key":"777","source":"4","target":"166"},{"key":"778","source":"4","target":"36"},{"key":"779","source":"5","target":"162"},{"key":"780","source":"12","target":"150"},{"key":"781","source":"12","target":"79"},{"key":"782","source":"12","target":"81"},{"key":"783","source":"12","target":"105"},{"key":"784","source":"12","target":"68"},{"key":"785","source":"12","target":"6"},{"key":"786","source":"12","target":"217"},{"key":"787","source":"12","target":"195"},{"key":"788","source":"12","target":"159"},{"key":"789","source":"12","target":"155"},{"key":"790","source":"12","target":"201"},{"key":"791","source":"12","target":"173"},{"key":"792","source":"12","target":"113"},{"key":"793","source":"12","target":"158"},{"key":"794","source":"12","target":"215"},{"key":"795","source":"12","target":"219"},{"key":"796","source":"12","target":"165"},{"key":"797","source":"12","target":"109"},{"key":"798","source":"12","target":"198"},{"key":"799","source":"12","target":"93"},{"key":"800","source":"12","target":"156"},{"key":"801","source":"12","target":"239"},{"key":"802","source":"12","target":"238"},{"key":"803","source":"12","target":"154"},{"key":"804","source":"12","target":"210"},{"key":"805","source":"12","target":"169"},{"key":"806","source":"12","target":"234"},{"key":"807","source":"12","target":"110"},{"key":"808","source":"12","target":"222"},{"key":"809","source":"12","target":"261"},{"key":"810","source":"12","target":"240"},{"key":"811","source":"12","target":"221"},{"key":"812","source":"12","target":"115"},{"key":"813","source":"12","target":"180"},{"key":"814","source":"13","target":"173"},{"key":"815","source":"13","target":"168"},{"key":"816","source":"13","target":"261"},{"key":"817","source":"13","target":"244"},{"key":"818","source":"13","target":"242"},{"key":"819","source":"13","target":"79"},{"key":"820","source":"13","target":"221"},{"key":"821","source":"13","target":"63"},{"key":"822","source":"15","target":"109"},{"key":"823","source":"15","target":"54"},{"key":"824","source":"15","target":"223"},{"key":"825","source":"15","target":"110"},{"key":"826","source":"15","target":"155"},{"key":"827","source":"15","target":"172"},{"key":"828","source":"15","target":"58"},{"key":"829","source":"15","target":"78"},{"key":"830","source":"15","target":"81"},{"key":"831","source":"15","target":"231"},{"key":"832","source":"15","target":"234"},{"key":"833","source":"15","target":"40"},{"key":"834","source":"15","target":"189"},{"key":"835","source":"15","target":"16"},{"key":"836","source":"15","target":"187"},{"key":"837","source":"15","target":"173"},{"key":"838","source":"15","target":"6"},{"key":"839","source":"15","target":"36"},{"key":"840","source":"16","target":"173"},{"key":"841","source":"16","target":"87"},{"key":"842","source":"16","target":"201"},{"key":"843","source":"16","target":"151"},{"key":"844","source":"16","target":"245"},{"key":"845","source":"16","target":"178"},{"key":"846","source":"16","target":"150"},{"key":"847","source":"16","target":"187"},{"key":"848","source":"18","target":"51"},{"key":"849","source":"20","target":"185"},{"key":"850","source":"20","target":"66"},{"key":"851","source":"20","target":"189"},{"key":"852","source":"20","target":"222"},{"key":"853","source":"20","target":"19"},{"key":"854","source":"20","target":"40"},{"key":"855","source":"20","target":"110"},{"key":"856","source":"21","target":"255"},{"key":"857","source":"21","target":"83"},{"key":"858","source":"21","target":"52"},{"key":"859","source":"21","target":"29"},{"key":"860","source":"21","target":"254"},{"key":"861","source":"22","target":"35"},{"key":"862","source":"23","target":"87"},{"key":"863","source":"23","target":"89"},{"key":"864","source":"23","target":"263"},{"key":"865","source":"23","target":"211"},{"key":"866","source":"23","target":"203"},{"key":"867","source":"23","target":"82"},{"key":"868","source":"23","target":"267"},{"key":"869","source":"23","target":"209"},{"key":"870","source":"23","target":"61"},{"key":"871","source":"23","target":"264"},{"key":"872","source":"23","target":"239"},{"key":"873","source":"23","target":"94"},{"key":"874","source":"23","target":"53"},{"key":"875","source":"23","target":"155"},{"key":"876","source":"23","target":"88"},{"key":"877","source":"23","target":"86"},{"key":"878","source":"23","target":"107"},{"key":"879","source":"23","target":"229"},{"key":"880","source":"23","target":"77"},{"key":"881","source":"23","target":"159"},{"key":"882","source":"23","target":"154"},{"key":"883","source":"23","target":"156"},{"key":"884","source":"23","target":"148"},{"key":"885","source":"0","target":"123"},{"key":"886","source":"0","target":"269"},{"key":"887","source":"0","target":"270"},{"key":"888","source":"0","target":"271"},{"key":"889","source":"0","target":"272"},{"key":"890","source":"0","target":"273"},{"key":"891","source":"0","target":"274"},{"key":"892","source":"0","target":"275"},{"key":"893","source":"0","target":"276"},{"key":"894","source":"0","target":"277"},{"key":"895","source":"0","target":"278"},{"key":"896","source":"0","target":"279"},{"key":"897","source":"0","target":"280"},{"key":"898","source":"0","target":"281"},{"key":"899","source":"0","target":"282"},{"key":"900","source":"0","target":"283"},{"key":"901","source":"0","target":"284"},{"key":"902","source":"0","target":"285"},{"key":"903","source":"0","target":"286"},{"key":"904","source":"0","target":"287"},{"key":"905","source":"0","target":"288"},{"key":"906","source":"0","target":"289"},{"key":"907","source":"0","target":"290"},{"key":"908","source":"0","target":"291"},{"key":"909","source":"0","target":"292"},{"key":"910","source":"0","target":"293"},{"key":"911","source":"0","target":"124"},{"key":"912","source":"0","target":"294"},{"key":"913","source":"0","target":"125"},{"key":"914","source":"0","target":"130"},{"key":"915","source":"0","target":"127"},{"key":"916","source":"0","target":"126"},{"key":"917","source":"0","target":"295"},{"key":"918","source":"0","target":"296"},{"key":"919","source":"0","target":"297"},{"key":"920","source":"0","target":"298"},{"key":"921","source":"0","target":"299"},{"key":"922","source":"0","target":"300"},{"key":"923","source":"0","target":"301"},{"key":"924","source":"0","target":"302"},{"key":"925","source":"0","target":"303"},{"key":"926","source":"0","target":"304"},{"key":"927","source":"0","target":"305"},{"key":"928","source":"0","target":"306"},{"key":"929","source":"0","target":"307"},{"key":"930","source":"0","target":"308"},{"key":"931","source":"0","target":"309"},{"key":"932","source":"0","target":"310"},{"key":"933","source":"0","target":"311"},{"key":"934","source":"0","target":"312"},{"key":"935","source":"0","target":"313"},{"key":"936","source":"0","target":"314"},{"key":"937","source":"0","target":"315"},{"key":"938","source":"0","target":"316"},{"key":"939","source":"0","target":"317"},{"key":"940","source":"0","target":"318"},{"key":"941","source":"0","target":"128"},{"key":"942","source":"0","target":"129"},{"key":"943","source":"0","target":"319"},{"key":"944","source":"0","target":"131"},{"key":"945","source":"0","target":"320"},{"key":"946","source":"0","target":"132"},{"key":"947","source":"0","target":"133"},{"key":"948","source":"0","target":"321"},{"key":"949","source":"0","target":"322"},{"key":"950","source":"3","target":"162"},{"key":"951","source":"3","target":"231"},{"key":"952","source":"3","target":"275"},{"key":"953","source":"3","target":"249"},{"key":"954","source":"3","target":"110"},{"key":"955","source":"3","target":"197"},{"key":"956","source":"4","target":"175"},{"key":"957","source":"4","target":"63"},{"key":"958","source":"4","target":"184"},{"key":"959","source":"4","target":"255"},{"key":"960","source":"5","target":"74"},{"key":"961","source":"5","target":"104"},{"key":"962","source":"12","target":"287"},{"key":"963","source":"12","target":"264"},{"key":"964","source":"12","target":"312"},{"key":"965","source":"12","target":"229"},{"key":"966","source":"12","target":"107"},{"key":"967","source":"12","target":"308"},{"key":"968","source":"12","target":"309"},{"key":"969","source":"12","target":"267"},{"key":"970","source":"15","target":"194"},{"key":"971","source":"15","target":"94"},{"key":"972","source":"15","target":"76"},{"key":"973","source":"15","target":"322"},{"key":"974","source":"15","target":"114"},{"key":"975","source":"15","target":"162"},{"key":"976","source":"15","target":"25"},{"key":"977","source":"16","target":"322"},{"key":"978","source":"16","target":"275"},{"key":"979","source":"16","target":"189"},{"key":"980","source":"16","target":"223"},{"key":"981","source":"16","target":"188"},{"key":"982","source":"16","target":"194"},{"key":"983","source":"16","target":"185"},{"key":"984","source":"16","target":"176"},{"key":"985","source":"16","target":"190"},{"key":"986","source":"16","target":"49"},{"key":"987","source":"16","target":"200"},{"key":"988","source":"16","target":"152"},{"key":"989","source":"16","target":"266"},{"key":"990","source":"16","target":"222"},{"key":"991","source":"16","target":"110"},{"key":"992","source":"16","target":"308"},{"key":"993","source":"16","target":"166"},{"key":"994","source":"20","target":"254"},{"key":"995","source":"20","target":"173"},{"key":"996","source":"20","target":"31"},{"key":"997","source":"20","target":"169"},{"key":"998","source":"20","target":"42"},{"key":"999","source":"21","target":"46"},{"key":"1000","source":"21","target":"19"},{"key":"1001","source":"24","target":"150"},{"key":"1002","source":"24","target":"114"},{"key":"1003","source":"24","target":"151"},{"key":"1004","source":"24","target":"203"},{"key":"1005","source":"25","target":"110"},{"key":"1006","source":"25","target":"38"},{"key":"1007","source":"25","target":"41"},{"key":"1008","source":"25","target":"72"},{"key":"1009","source":"25","target":"181"},{"key":"1010","source":"25","target":"112"},{"key":"1011","source":"25","target":"67"},{"key":"1012","source":"25","target":"294"},{"key":"1013","source":"25","target":"54"},{"key":"1014","source":"25","target":"95"},{"key":"1015","source":"25","target":"77"},{"key":"1016","source":"25","target":"315"},{"key":"1017","source":"25","target":"75"},{"key":"1018","source":"25","target":"76"},{"key":"1019","source":"25","target":"94"},{"key":"1020","source":"25","target":"219"},{"key":"1021","source":"25","target":"105"},{"key":"1022","source":"25","target":"47"},{"key":"1023","source":"25","target":"109"},{"key":"1024","source":"25","target":"103"},{"key":"1025","source":"25","target":"220"},{"key":"1026","source":"25","target":"209"},{"key":"1027","source":"25","target":"101"},{"key":"1028","source":"25","target":"149"},{"key":"1029","source":"25","target":"224"},{"key":"1030","source":"25","target":"78"},{"key":"1031","source":"25","target":"150"},{"key":"1032","source":"25","target":"235"},{"key":"1033","source":"25","target":"215"},{"key":"1034","source":"25","target":"179"},{"key":"1035","source":"25","target":"158"},{"key":"1036","source":"25","target":"233"},{"key":"1037","source":"25","target":"297"},{"key":"1038","source":"25","target":"214"},{"key":"1039","source":"25","target":"195"},{"key":"1040","source":"26","target":"166"},{"key":"1041","source":"26","target":"74"},{"key":"1042","source":"26","target":"17"},{"key":"1043","source":"26","target":"98"},{"key":"1044","source":"26","target":"195"},{"key":"1045","source":"26","target":"67"},{"key":"1046","source":"26","target":"196"},{"key":"1047","source":"26","target":"216"},{"key":"1048","source":"26","target":"78"},{"key":"1049","source":"27","target":"2"},{"key":"1050","source":"27","target":"31"},{"key":"1051","source":"27","target":"32"},{"key":"1052","source":"27","target":"285"},{"key":"1053","source":"27","target":"320"},{"key":"1054","source":"27","target":"294"},{"key":"1055","source":"27","target":"247"},{"key":"1056","source":"27","target":"203"},{"key":"1057","source":"27","target":"292"},{"key":"1058","source":"27","target":"17"},{"key":"1059","source":"27","target":"60"},{"key":"1060","source":"27","target":"104"},{"key":"1061","source":"27","target":"91"},{"key":"1062","source":"28","target":"176"},{"key":"1063","source":"28","target":"322"},{"key":"1064","source":"29","target":"177"},{"key":"1065","source":"29","target":"270"},{"key":"1066","source":"29","target":"322"},{"key":"1067","source":"29","target":"173"},{"key":"1068","source":"29","target":"268"},{"key":"1069","source":"29","target":"28"},{"key":"1070","source":"29","target":"52"},{"key":"1071","source":"29","target":"36"},{"key":"1072","source":"29","target":"42"},{"key":"1073","source":"29","target":"19"},{"key":"1074","source":"29","target":"1"},{"key":"1075","source":"29","target":"160"},{"key":"1076","source":"29","target":"255"},{"key":"1077","source":"29","target":"256"},{"key":"1078","source":"29","target":"185"},{"key":"1079","source":"29","target":"20"},{"key":"1080","source":"29","target":"83"},{"key":"1081","source":"29","target":"206"},{"key":"1082","source":"0","target":"137"},{"key":"1083","source":"0","target":"135"},{"key":"1084","source":"0","target":"136"},{"key":"1085","source":"0","target":"134"},{"key":"1086","source":"0","target":"138"},{"key":"1087","source":"0","target":"141"},{"key":"1088","source":"0","target":"140"},{"key":"1089","source":"0","target":"139"},{"key":"1090","source":"0","target":"142"},{"key":"1091","source":"0","target":"144"},{"key":"1092","source":"0","target":"145"},{"key":"1093","source":"0","target":"146"},{"key":"1094","source":"0","target":"323"},{"key":"1095","source":"0","target":"147"},{"key":"1096","source":"3","target":"273"},{"key":"1097","source":"3","target":"113"},{"key":"1098","source":"3","target":"200"},{"key":"1099","source":"3","target":"222"},{"key":"1100","source":"3","target":"317"},{"key":"1101","source":"3","target":"93"},{"key":"1102","source":"3","target":"171"},{"key":"1103","source":"3","target":"311"},{"key":"1104","source":"3","target":"309"},{"key":"1105","source":"3","target":"293"},{"key":"1106","source":"4","target":"66"},{"key":"1107","source":"4","target":"157"},{"key":"1108","source":"4","target":"20"},{"key":"1109","source":"4","target":"19"},{"key":"1110","source":"4","target":"114"},{"key":"1111","source":"4","target":"257"},{"key":"1112","source":"5","target":"254"},{"key":"1113","source":"15","target":"297"},{"key":"1114","source":"15","target":"232"},{"key":"1115","source":"15","target":"302"},{"key":"1116","source":"15","target":"301"},{"key":"1117","source":"15","target":"156"},{"key":"1118","source":"15","target":"183"},{"key":"1119","source":"16","target":"231"},{"key":"1120","source":"16","target":"271"},{"key":"1121","source":"16","target":"235"},{"key":"1122","source":"16","target":"279"},{"key":"1123","source":"16","target":"105"},{"key":"1124","source":"21","target":"248"},{"key":"1125","source":"21","target":"193"},{"key":"1126","source":"24","target":"82"},{"key":"1127","source":"24","target":"54"},{"key":"1128","source":"25","target":"227"},{"key":"1129","source":"25","target":"261"},{"key":"1130","source":"25","target":"167"},{"key":"1131","source":"25","target":"301"},{"key":"1132","source":"25","target":"240"},{"key":"1133","source":"25","target":"205"},{"key":"1134","source":"25","target":"201"},{"key":"1135","source":"25","target":"162"},{"key":"1136","source":"25","target":"104"},{"key":"1137","source":"25","target":"222"},{"key":"1138","source":"25","target":"259"},{"key":"1139","source":"25","target":"251"},{"key":"1140","source":"25","target":"262"},{"key":"1141","source":"25","target":"115"},{"key":"1142","source":"25","target":"258"},{"key":"1143","source":"25","target":"246"},{"key":"1144","source":"25","target":"177"},{"key":"1145","source":"25","target":"286"},{"key":"1146","source":"25","target":"276"},{"key":"1147","source":"25","target":"319"},{"key":"1148","source":"25","target":"59"},{"key":"1149","source":"25","target":"253"},{"key":"1150","source":"25","target":"245"},{"key":"1151","source":"25","target":"283"},{"key":"1152","source":"25","target":"255"},{"key":"1153","source":"25","target":"257"},{"key":"1154","source":"25","target":"108"},{"key":"1155","source":"25","target":"204"},{"key":"1156","source":"25","target":"275"},{"key":"1157","source":"25","target":"243"},{"key":"1158","source":"25","target":"217"},{"key":"1159","source":"25","target":"231"},{"key":"1160","source":"25","target":"208"},{"key":"1161","source":"25","target":"111"},{"key":"1162","source":"25","target":"84"},{"key":"1163","source":"25","target":"200"},{"key":"1164","source":"25","target":"320"},{"key":"1165","source":"25","target":"322"},{"key":"1166","source":"25","target":"270"},{"key":"1167","source":"25","target":"192"},{"key":"1168","source":"25","target":"308"},{"key":"1169","source":"25","target":"213"},{"key":"1170","source":"25","target":"203"},{"key":"1171","source":"25","target":"207"},{"key":"1172","source":"25","target":"313"},{"key":"1173","source":"25","target":"225"},{"key":"1174","source":"25","target":"291"},{"key":"1175","source":"26","target":"3"},{"key":"1176","source":"26","target":"254"},{"key":"1177","source":"26","target":"52"},{"key":"1178","source":"26","target":"32"},{"key":"1179","source":"26","target":"199"},{"key":"1180","source":"26","target":"277"},{"key":"1181","source":"27","target":"215"},{"key":"1182","source":"27","target":"57"},{"key":"1183","source":"27","target":"249"},{"key":"1184","source":"28","target":"56"},{"key":"1185","source":"28","target":"200"},{"key":"1186","source":"29","target":"40"},{"key":"1187","source":"29","target":"283"},{"key":"1188","source":"29","target":"202"},{"key":"1189","source":"29","target":"308"},{"key":"1190","source":"29","target":"110"},{"key":"1191","source":"3","target":"304"},{"key":"1192","source":"3","target":"310"},{"key":"1193","source":"3","target":"278"},{"key":"1194","source":"3","target":"308"},{"key":"1195","source":"3","target":"281"},{"key":"1196","source":"4","target":"116"},{"key":"1197","source":"4","target":"250"},{"key":"1198","source":"4","target":"31"},{"key":"1199","source":"4","target":"6"},{"key":"1200","source":"4","target":"269"},{"key":"1201","source":"4","target":"200"},{"key":"1202","source":"4","target":"318"},{"key":"1203","source":"5","target":"278"},{"key":"1204","source":"5","target":"314"},{"key":"1205","source":"5","target":"295"},{"key":"1206","source":"5","target":"77"},{"key":"1207","source":"5","target":"298"},{"key":"1208","source":"5","target":"308"},{"key":"1209","source":"15","target":"82"},{"key":"1210","source":"15","target":"153"},{"key":"1211","source":"15","target":"240"},{"key":"1212","source":"15","target":"265"},{"key":"1213","source":"15","target":"61"},{"key":"1214","source":"15","target":"186"},{"key":"1215","source":"15","target":"199"},{"key":"1216","source":"16","target":"172"},{"key":"1217","source":"16","target":"210"},{"key":"1218","source":"16","target":"293"},{"key":"1219","source":"21","target":"56"},{"key":"1220","source":"21","target":"1"},{"key":"1221","source":"21","target":"256"},{"key":"1222","source":"21","target":"178"},{"key":"1223","source":"25","target":"272"},{"key":"1224","source":"25","target":"247"},{"key":"1225","source":"25","target":"290"},{"key":"1226","source":"25","target":"279"},{"key":"1227","source":"25","target":"288"},{"key":"1228","source":"25","target":"223"},{"key":"1229","source":"25","target":"274"},{"key":"1230","source":"25","target":"182"},{"key":"1231","source":"25","target":"260"},{"key":"1232","source":"25","target":"284"},{"key":"1233","source":"25","target":"241"},{"key":"1234","source":"25","target":"282"},{"key":"1235","source":"25","target":"102"},{"key":"1236","source":"25","target":"236"},{"key":"1237","source":"25","target":"230"},{"key":"1238","source":"25","target":"280"},{"key":"1239","source":"25","target":"289"},{"key":"1240","source":"25","target":"226"},{"key":"1241","source":"25","target":"15"},{"key":"1242","source":"25","target":"299"},{"key":"1243","source":"25","target":"306"},{"key":"1244","source":"25","target":"281"},{"key":"1245","source":"25","target":"303"},{"key":"1246","source":"25","target":"316"},{"key":"1247","source":"25","target":"323"},{"key":"1248","source":"25","target":"311"},{"key":"1249","source":"25","target":"304"},{"key":"1250","source":"25","target":"305"},{"key":"1251","source":"25","target":"267"},{"key":"1252","source":"25","target":"300"},{"key":"1253","source":"25","target":"256"},{"key":"1254","source":"25","target":"312"},{"key":"1255","source":"25","target":"309"},{"key":"1256","source":"25","target":"252"},{"key":"1257","source":"25","target":"287"},{"key":"1258","source":"25","target":"285"},{"key":"1259","source":"25","target":"266"},{"key":"1260","source":"25","target":"307"},{"key":"1261","source":"25","target":"296"},{"key":"1262","source":"25","target":"228"},{"key":"1263","source":"26","target":"310"},{"key":"1264","source":"26","target":"321"},{"key":"1265","source":"26","target":"237"},{"key":"1266","source":"26","target":"57"},{"key":"1267","source":"26","target":"303"},{"key":"1268","source":"26","target":"75"},{"key":"1269","source":"26","target":"180"},{"key":"1270","source":"26","target":"218"},{"key":"1271","source":"26","target":"49"},{"key":"1272","source":"28","target":"255"},{"key":"1273","source":"28","target":"308"},{"key":"1274","source":"28","target":"1"},{"key":"1275","source":"28","target":"256"},{"key":"1276","source":"28","target":"29"},{"key":"1277","source":"31","target":"2"},{"key":"1278","source":"31","target":"169"},{"key":"1279","source":"31","target":"184"},{"key":"1280","source":"31","target":"40"},{"key":"1281","source":"31","target":"20"},{"key":"1282","source":"31","target":"19"},{"key":"1283","source":"32","target":"260"},{"key":"1284","source":"32","target":"240"},{"key":"1285","source":"32","target":"27"},{"key":"1286","source":"33","target":"15"},{"key":"1287","source":"33","target":"291"},{"key":"1288","source":"33","target":"277"},{"key":"1289","source":"33","target":"76"},{"key":"1290","source":"33","target":"81"},{"key":"1291","source":"33","target":"301"},{"key":"1292","source":"33","target":"309"},{"key":"1293","source":"33","target":"115"},{"key":"1294","source":"33","target":"44"},{"key":"1295","source":"33","target":"75"},{"key":"1296","source":"33","target":"107"},{"key":"1297","source":"33","target":"54"},{"key":"1298","source":"33","target":"285"},{"key":"1299","source":"34","target":"159"},{"key":"1300","source":"34","target":"309"},{"key":"1301","source":"34","target":"156"},{"key":"1302","source":"34","target":"312"},{"key":"1303","source":"34","target":"101"},{"key":"1304","source":"34","target":"212"},{"key":"1305","source":"34","target":"301"}]}